{"nm":"Comp 1","ddd":0,"h":1920,"w":1080,"meta":{"g":"@lottiefiles/toolkit-js 0.70.6"},"layers":[{"ty":4,"nm":"udrabstegn Outlines","sr":1,"st":0,"op":105,"ip":0,"ln":"70","hasMask":false,"ao":0,"ks":{"a":{"a":0,"k":[11.69,22.745,0]},"s":{"a":0,"k":[100,100]},"p":{"a":0,"k":[46,45.805,0]},"r":{"a":0,"k":0},"sa":{"a":0,"k":0},"o":{"a":0,"k":100}},"shapes":[{"ty":"gr","nm":"Group 1","it":[{"ty":"sh","nm":"Path 1","d":1,"ks":{"a":0,"k":{"c":true,"i":[[1.7,0.51],[0.81,1.5],[-0.52,1.74],[-1.51,0.83],[-1.74,-0.52],[-0.83,-1.53],[0.51,-1.7],[1.52,-0.8]],"o":[[-1.74,-0.52],[-0.81,-1.51],[0.52,-1.74],[1.51,-0.84],[1.74,0.52],[0.83,1.54],[-0.51,1.7],[-1.53,0.81]],"v":[[-6.65,21.985],[-10.48,18.945],[-10.92,14.075],[-7.89,10.275],[-3.01,9.805],[0.78,12.865],[1.26,17.715],[-1.81,21.535]]}}},{"ty":"sh","nm":"Path 2","d":1,"ks":{"a":0,"k":{"c":true,"i":[[0,0],[0.75,1.27],[-0.48,1.48],[-0.43,1.49],[-0.32,1.42],[-0.29,1.56],[-0.36,1.97],[-0.87,0.72],[-1.13,0.23],[-1.08,-0.32],[-0.82,-0.81],[-0.33,-1.07],[0.48,-1.12],[0.62,-1.46],[0.51,-1.36],[0.47,-1.49],[0.45,-1.99],[1.35,-0.63],[1.41,0.42]],"o":[[-1.41,-0.42],[-0.75,-1.26],[0.71,-1.91],[0.42,-1.5],[0.31,-1.42],[0.28,-1.56],[0.22,-1.2],[0.87,-0.71],[1.13,-0.23],[1.08,0.32],[0.82,0.81],[0.33,1.07],[-0.78,1.85],[-0.62,1.46],[-0.51,1.36],[-0.47,1.49],[-0.36,1.52],[-1.34,0.64],[0,0]],"v":[[-2.45,7.925],[-5.69,5.395],[-6.09,1.275],[-4.39,-3.835],[-3.28,-8.215],[-2.38,-12.685],[-1.41,-17.985],[0.23,-20.855],[3.22,-22.265],[6.53,-22.125],[9.38,-20.425],[11.11,-17.605],[10.9,-14.315],[8.81,-9.355],[7.11,-5.125],[5.63,-0.855],[4.25,4.355],[1.69,7.585],[-2.44,7.915]]}}},{"ty":"fl","nm":"Fill 1","c":{"a":0,"k":[1,1,1]},"r":1,"o":{"a":0,"k":100}},{"ty":"tr","a":{"a":0,"k":[0,0]},"s":{"a":0,"k":[100,100]},"p":{"a":0,"k":[11.69,22.745]},"r":{"a":0,"k":0},"sa":{"a":0,"k":0},"o":{"a":0,"k":100}}]}],"ind":1,"parent":2},{"ty":4,"nm":"mork_blaa_boble Outlines","sr":1,"st":0,"op":105,"ip":0,"ln":"69","hasMask":false,"ao":0,"ks":{"a":{"a":0,"k":[45.935,47.83,0]},"s":{"a":1,"k":[{"s":[100,100,100],"i":{"x":[0.667,0.667,0.667],"y":[1,1,1]},"o":{"x":[0.333,0.333,0.333],"y":[0,0,0]},"t":30},{"s":[125,125,100.806],"i":{"x":[0.667,0.667,0.667],"y":[1,1,1]},"o":{"x":[0.333,0.333,0.333],"y":[0,0,0]},"t":45},{"s":[-125,125,100],"i":{"x":[0.667,0.667,0.667],"y":[1,1,1]},"o":{"x":[0.333,0.333,0.333],"y":[0,0,0]},"t":57.999},{"s":[-75,75,88.235],"i":{"x":[0.667,0.667,0.667],"y":[1,1,1]},"o":{"x":[0.167,0.167,0.167],"y":[0,0,0]},"t":104.999}]},"p":{"a":1,"k":[{"o":{"x":0.333,"y":0},"i":{"x":0.667,"y":1},"s":[507.755,971.215,0],"t":30},{"o":{"x":0.333,"y":0},"i":{"x":0.667,"y":1},"s":[494.321,986.142,0],"t":45},{"o":{"x":0.333,"y":0},"i":{"x":0.667,"y":1},"s":[597.311,931.425,0],"t":57.999},{"s":[1142.151,941.874,0],"t":104.999}]},"r":{"a":1,"k":[{"o":{"x":0.333,"y":0},"i":{"x":0.667,"y":1},"s":[0],"t":30},{"o":{"x":0.333,"y":0},"i":{"x":0.667,"y":1},"s":[10],"t":45},{"o":{"x":0.333,"y":0},"i":{"x":0.667,"y":1},"s":[-16],"t":57.999},{"s":[71],"t":104.999}]},"sa":{"a":0,"k":0},"o":{"a":0,"k":100}},"shapes":[{"ty":"gr","nm":"Group 1","it":[{"ty":"sh","nm":"Path 1","d":1,"ks":{"a":0,"k":{"c":true,"i":[[0,-25.12],[25.13,0],[5.13,2.01],[6.8,0],[3.51,2.07],[-1.27,7.06],[0,11.46],[-25.12,0]],"o":[[0,25.12],[-5.83,0],[-4.38,4.5],[-4.38,0],[6.01,-3.45],[-7,-7.99],[0,-25.12],[25.12,0]],"v":[[45.685,-2.095],[0.195,43.395],[-16.345,40.285],[-33.655,47.585],[-45.685,44.325],[-34.045,27.835],[-45.285,-2.095],[0.195,-47.585]]}}},{"ty":"fl","nm":"Fill 1","c":{"a":0,"k":[0,0.1451,0.2745]},"r":1,"o":{"a":0,"k":100}},{"ty":"tr","a":{"a":0,"k":[0,0]},"s":{"a":0,"k":[100,100]},"p":{"a":0,"k":[45.935,47.835]},"r":{"a":0,"k":0},"sa":{"a":0,"k":0},"o":{"a":0,"k":100}}]}],"ind":2},{"ty":4,"nm":"sporgsmaaltegn Outlines","sr":1,"st":0,"op":105,"ip":0,"ln":"68","hasMask":false,"ao":0,"ks":{"a":{"a":0,"k":[14.6,22.9,0]},"s":{"a":1,"k":[{"s":[100,100,100],"i":{"x":[0.667,0.667,0.667],"y":[1,1,1]},"o":{"x":[0.333,0.333,0.333],"y":[0,0,0]},"t":45},{"s":[-100,100,100],"i":{"x":[0.667,0.667,0.667],"y":[1,1,1]},"o":{"x":[0.167,0.167,0.167],"y":[0,0,0]},"t":57.999}]},"p":{"a":1,"k":[{"o":{"x":0.333,"y":0},"i":{"x":0.667,"y":1},"s":[42.39,45.77,0],"t":45},{"s":[47.827,46.002,0],"t":57.999}]},"r":{"a":1,"k":[{"o":{"x":0.333,"y":0},"i":{"x":0.667,"y":1},"s":[0],"t":45},{"s":[-49],"t":57.999}]},"sa":{"a":0,"k":0},"o":{"a":0,"k":100}},"shapes":[{"ty":"gr","nm":"Group 1","it":[{"ty":"sh","nm":"Path 1","d":1,"ks":{"a":0,"k":{"c":true,"i":[[0,0],[1.52,0.77],[0.57,1.72],[-0.76,1.55],[-1.72,0.57],[-1.56,-0.78],[-0.56,-1.68],[0.78,-1.53],[1.67,-0.56]],"o":[[-1.72,0.57],[-1.52,-0.77],[-0.57,-1.72],[0.76,-1.55],[1.68,-0.56],[1.56,0.78],[0.56,1.68],[-0.79,1.53],[0,0]],"v":[[9.77,22.08],[4.9,21.79],[1.75,18.06],[2.05,13.22],[5.77,10.04],[10.62,10.37],[13.79,14.06],[13.47,18.94],[9.78,22.08]]}}},{"ty":"sh","nm":"Path 2","d":1,"ks":{"a":0,"k":{"c":true,"i":[[0,0],[1.23,0.57],[0.52,1.28],[0.1,0.99],[-0.35,0.84],[-0.75,1.02],[-0.48,0.63],[-0.14,0.48],[0.2,0.62],[0.74,0.11],[0.66,-0.22],[0.4,-0.43],[0.49,-0.57],[1.38,-0.17],[1.06,0.46],[0.48,0.98],[-0.17,1.12],[-0.75,0.89],[-3.32,1.1],[-2.37,-0.42],[-1.7,-1.4],[-0.7,-2.09],[0.05,-1.22],[0.43,-0.91],[0.59,-0.77],[0.57,-0.74],[-0.01,-0.38],[-0.3,-0.63],[0.3,-0.94],[0.76,-0.75],[0.98,-0.33]],"o":[[-1.47,0.49],[-1.23,-0.57],[-0.57,-1.45],[-0.1,-0.99],[0.36,-0.84],[0.84,-1.15],[0.47,-0.63],[0.14,-0.48],[-0.29,-0.86],[-0.74,-0.12],[-0.49,0.16],[-0.4,0.43],[-0.82,0.96],[-1.38,0.16],[-1.16,-0.48],[-0.48,-0.98],[0.17,-1.12],[1.97,-2.29],[2.66,-0.89],[2.36,0.42],[1.7,1.4],[0.54,1.64],[-0.05,1.22],[-0.43,0.91],[-0.59,0.77],[-0.44,0.6],[0.01,0.38],[0.4,0.78],[-0.3,0.94],[-0.75,0.75],[0,0]],"v":[[4.9,7.67],[0.84,7.55],[-1.79,4.78],[-2.8,1.13],[-2.42,-1.62],[-0.76,-4.42],[1.22,-7.09],[2.13,-8.76],[2.03,-10.4],[0.49,-11.86],[-1.61,-11.71],[-2.95,-10.82],[-4.29,-9.32],[-7.59,-7.64],[-11.25,-8.09],[-13.71,-10.27],[-14.18,-13.42],[-12.8,-16.44],[-4.87,-21.53],[2.67,-22.23],[8.76,-19.51],[12.34,-14.29],[13.08,-10],[12.37,-6.8],[10.85,-4.28],[9.11,-2.03],[8.47,-0.56],[8.94,0.96],[9.08,3.54],[7.5,6.08],[4.9,7.7]]}}},{"ty":"fl","nm":"Fill 1","c":{"a":0,"k":[1,1,1]},"r":1,"o":{"a":0,"k":100}},{"ty":"tr","a":{"a":0,"k":[0,0]},"s":{"a":0,"k":[100,100]},"p":{"a":0,"k":[14.6,22.9]},"r":{"a":0,"k":0},"sa":{"a":0,"k":0},"o":{"a":0,"k":100}}]}],"ind":3,"parent":4},{"ty":4,"nm":"lys_blaa_boble Outlines","sr":1,"st":0,"op":105,"ip":0,"ln":"67","hasMask":false,"ao":0,"ks":{"a":{"a":0,"k":[45.935,47.83,0]},"s":{"a":1,"k":[{"s":[100,100,100],"i":{"x":[0.667,0.667,0.667],"y":[1,1,1]},"o":{"x":[0.333,0.333,0.333],"y":[0,0,0]},"t":30},{"s":[125,125,100.806],"i":{"x":[0.667,0.667,0.667],"y":[1,1,1]},"o":{"x":[0.333,0.333,0.333],"y":[0,0,0]},"t":45},{"s":[-125,125,100],"i":{"x":[0.667,0.667,0.667],"y":[1,1,1]},"o":{"x":[0.333,0.333,0.333],"y":[0,0,0]},"t":57.999},{"s":[-75,75,88.235],"i":{"x":[0.667,0.667,0.667],"y":[1,1,1]},"o":{"x":[0.167,0.167,0.167],"y":[0,0,0]},"t":104.999}]},"p":{"a":1,"k":[{"o":{"x":0.333,"y":0},"i":{"x":0.667,"y":1},"s":[571.935,950.83,0],"t":30},{"o":{"x":0.333,"y":0},"i":{"x":0.667,"y":1},"s":[597.311,931.425,0],"t":45},{"o":{"x":0.333,"y":0},"i":{"x":0.667,"y":1},"s":[494.321,986.142,0],"t":57.999},{"s":[-65.446,986.142,0],"t":104.999}]},"r":{"a":1,"k":[{"o":{"x":0.333,"y":0},"i":{"x":0.667,"y":1},"s":[0],"t":30},{"o":{"x":0.333,"y":0},"i":{"x":0.667,"y":1},"s":[-16],"t":45},{"o":{"x":0.333,"y":0},"i":{"x":0.667,"y":1},"s":[10],"t":57.999},{"s":[-86],"t":104.999}]},"sa":{"a":0,"k":0},"o":{"a":0,"k":100}},"shapes":[{"ty":"gr","nm":"Group 1","it":[{"ty":"sh","nm":"Path 1","d":1,"ks":{"a":0,"k":{"c":true,"i":[[-6.01,-3.45],[4.39,0],[4.38,4.5],[5.84,0],[0,25.13],[-25.12,0],[0,-25.12],[7.01,-7.99]],"o":[[-3.51,2.06],[-6.79,0],[-5.13,2],[-25.12,0],[0,-25.13],[25.12,0],[0,11.47],[1.27,7.06]],"v":[[45.685,44.33],[33.655,47.58],[16.355,40.29],[-0.195,43.39],[-45.685,-2.1],[-0.195,-47.58],[45.295,-2.1],[34.045,27.84]]}}},{"ty":"fl","nm":"Fill 1","c":{"a":0,"k":[0.2314,0.5098,0.9647]},"r":1,"o":{"a":0,"k":100}},{"ty":"tr","a":{"a":0,"k":[0,0]},"s":{"a":0,"k":[100,100]},"p":{"a":0,"k":[45.935,47.83]},"r":{"a":0,"k":0},"sa":{"a":0,"k":0},"o":{"a":0,"k":100}}]}],"ind":4},{"ty":4,"nm":"Layer 1 Outlines","sr":1,"st":0,"op":105,"ip":0,"ln":"66","hasMask":false,"ao":0,"ks":{"a":{"a":0,"k":[192.09,36.795,0]},"s":{"a":1,"k":[{"s":[100,100,100],"i":{"x":[0.667,0.667,0.667],"y":[1,1,1]},"o":{"x":[0.333,0.333,0.333],"y":[0,0,0]},"t":28},{"s":[57,57,100],"i":{"x":[0.833,0.833,0.833],"y":[1,1,1]},"o":{"x":[0.167,0.167,0.167],"y":[0,0,0]},"t":41},{"s":[0,0,100],"i":{"x":[0.833,0.833,0.833],"y":[1,1,1]},"o":{"x":[0.167,0.167,0.167],"y":[0,0,0]},"t":49.999}]},"p":{"a":1,"k":[{"o":{"x":0.333,"y":0},"i":{"x":0.667,"y":1},"s":[540,1044.832,0],"t":28},{"s":[540,983.832,0],"t":45}]},"r":{"a":0,"k":0},"sa":{"a":0,"k":0},"o":{"a":0,"k":100}},"shapes":[{"ty":"gr","nm":"Group 1","it":[{"ty":"sh","nm":"Path 1","d":1,"ks":{"a":0,"k":{"c":true,"i":[[0,0],[2.24,0.52],[1.43,0.44],[1,1.55],[-0.44,2.05],[-1.09,1.25],[-1.49,0.47],[-1.49,-0.8],[-1.12,-0.38],[-1.68,0],[-0.75,0.65],[0,1.18],[0.87,0.62],[1.68,0.18],[1.9,0.34],[1.4,0.78],[0.78,1.43],[0,2.43],[-1.55,2.46],[-2.7,1.33],[-3.61,0],[-2.02,-0.47],[-1.37,-0.56],[-1,-1.52],[0.49,-2.11],[1.15,-1.09],[1.52,-0.28],[1.43,0.88],[0.9,0.31],[1.18,0],[0.41,-0.31],[0,-0.62],[-0.53,-0.44],[-2.37,-0.25],[-2.46,-1.03],[-1.46,-2.05],[0,-3.42],[1.77,-2.52],[3.17,-1.21],[4.11,0]],"o":[[-2.61,0],[-2.24,-0.53],[-1.74,-0.75],[-1,-1.55],[0.31,-1.49],[1.09,-1.24],[1.49,-0.47],[0.93,0.5],[1.12,0.37],[1.31,0],[0.75,-0.65],[0,-0.93],[-0.87,-0.62],[-2.12,-0.31],[-1.9,-0.34],[-1.4,-0.78],[-0.78,-1.43],[0,-3.3],[1.56,-2.46],[2.71,-1.34],[2.24,0],[2.02,0.47],[1.74,0.81],[0.99,1.53],[-0.31,1.43],[-1.15,1.09],[-1.53,0.28],[-0.81,-0.5],[-0.9,-0.31],[-0.75,0],[-0.41,0.31],[0,0.62],[0.53,0.44],[3.05,0.37],[2.46,1.03],[1.46,2.05],[0,3.8],[-1.77,2.52],[-3.17,1.21],[0,0]],"v":[[-1.395,25.385],[-8.675,24.595],[-14.185,23.145],[-18.295,19.695],[-19.135,14.285],[-17.035,10.175],[-13.165,7.605],[-8.685,8.115],[-5.605,9.425],[-1.405,9.985],[1.675,9.005],[2.795,6.255],[1.485,3.925],[-2.345,2.715],[-8.365,1.735],[-13.315,0.055],[-16.585,-3.255],[-17.755,-9.045],[-15.425,-17.685],[-9.035,-23.375],[0.445,-25.385],[6.835,-24.685],[11.925,-23.145],[16.035,-19.645],[16.785,-14.185],[14.595,-10.405],[10.585,-8.355],[6.155,-9.245],[3.585,-10.455],[0.455,-10.925],[-1.275,-10.455],[-1.885,-9.055],[-1.095,-7.465],[3.245,-6.435],[11.505,-4.335],[17.385,0.285],[19.575,8.495],[16.915,17.965],[9.495,23.565],[-1.425,25.385]]}}},{"ty":"fl","nm":"Fill 1","c":{"a":0,"k":[0,0.1451,0.2745]},"r":1,"o":{"a":0,"k":100}},{"ty":"tr","a":{"a":0,"k":[0,0]},"s":{"a":0,"k":[100,100]},"p":{"a":0,"k":[364.355,29.275]},"r":{"a":0,"k":0},"sa":{"a":0,"k":0},"o":{"a":0,"k":100}}]},{"ty":"gr","nm":"Group 2","it":[{"ty":"sh","nm":"Path 1","d":1,"ks":{"a":0,"k":{"c":true,"i":[[0,0],[1.46,0.71],[0.87,1.28],[-0.13,1.68],[-0.1,3.52],[0.09,3.58],[0.31,4.23],[-1.65,1.33],[-2.12,0],[-0.69,-0.37],[-0.38,-0.75],[-0.28,-0.22],[-0.25,0.18],[-0.78,0.47],[-1.05,0.5],[-1.4,0.31],[-1.74,0],[-0.59,-0.03],[-0.44,-0.06],[-1.25,-1.86],[0.93,-2.86],[1.06,-1.06],[1.31,-0.31],[1.25,0.93],[0.28,0.13],[0.37,0],[1.09,-0.78],[0.65,-1.33],[0,-1.68],[-0.04,-1.83],[-0.12,-1.8],[-0.31,-2.55],[0.84,-1.34],[1.53,-0.75],[1.81,0]],"o":[[-1.62,0],[-1.46,-0.72],[-0.87,-1.28],[0.31,-4.36],[0.09,-3.52],[-0.09,-3.58],[-0.19,-2.18],[1.65,-1.34],[1.12,0],[0.68,0.37],[0.43,0.62],[0.28,0.22],[0.5,-0.37],[0.78,-0.47],[1.06,-0.5],[1.4,-0.31],[0.62,0],[0.59,0.03],[2.24,0.25],[1.24,1.87],[-0.44,1.31],[-1.06,1.06],[-1.31,0.31],[-0.25,-0.19],[-0.28,-0.12],[-1.18,0],[-1.09,0.78],[-0.65,1.34],[0,2.61],[0.03,1.84],[0.12,1.81],[0.25,1.68],[-0.84,1.34],[-1.53,0.75],[0,0]],"v":[[-9.19,25.385],[-13.81,24.315],[-17.31,21.325],[-18.43,16.895],[-17.82,5.085],[-17.82,-5.555],[-18.43,-17.265],[-16.24,-22.535],[-10.59,-24.545],[-7.88,-23.985],[-6.29,-22.305],[-5.22,-21.045],[-4.43,-20.995],[-2.52,-22.255],[0.23,-23.705],[3.92,-24.915],[8.63,-25.385],[10.45,-25.335],[11.99,-25.195],[17.22,-22.025],[17.69,-14.935],[15.45,-11.385],[11.9,-9.335],[8.07,-10.265],[7.28,-10.735],[6.3,-10.925],[2.89,-9.755],[0.28,-6.585],[-0.7,-2.055],[-0.65,4.615],[-0.42,10.075],[0.23,16.605],[-0.66,21.135],[-4.21,24.265],[-9.21,25.385]]}}},{"ty":"fl","nm":"Fill 1","c":{"a":0,"k":[0,0.1451,0.2745]},"r":1,"o":{"a":0,"k":100}},{"ty":"tr","a":{"a":0,"k":[0,0]},"s":{"a":0,"k":[100,100]},"p":{"a":0,"k":[325.47,29.275]},"r":{"a":0,"k":0},"sa":{"a":0,"k":0},"o":{"a":0,"k":100}}]},{"ty":"gr","nm":"Group 3","it":[{"ty":"sh","nm":"Path 1","d":1,"ks":{"a":0,"k":{"c":true,"i":[[-0.63,0.06],[-0.75,0.56],[0,0.93],[0.31,0.5],[0.53,0.25],[0.68,0],[0.77,-0.37],[0.49,-0.75],[0,-1.06],[-0.62,-0.28]],"o":[[2.61,-0.12],[0.75,-0.56],[0,-0.75],[-0.31,-0.5],[-0.53,-0.25],[-1.06,0],[-0.78,0.37],[-0.5,0.75],[0,0.62],[0.62,0.28]],"v":[[-1.445,-7.37],[3.595,-8.4],[4.715,-10.64],[4.245,-12.51],[2.985,-13.63],[1.165,-14],[-1.585,-13.44],[-3.495,-11.76],[-4.245,-9.05],[-3.315,-7.7]]}}},{"ty":"sh","nm":"Path 2","d":1,"ks":{"a":0,"k":{"c":true,"i":[[0,0],[2.96,1.62],[1.71,2.46],[0.71,2.58],[0,2.05],[0,0],[-0.71,2.96],[-1.71,2.55],[-2.96,1.61],[-4.49,0],[-2.68,-1.08],[-1.49,-1.65],[-0.59,-1.84],[0,-1.43],[0.93,-1.59],[1.53,-0.9],[1.96,-0.44],[2.09,-0.22],[1.93,-0.19],[0.47,-0.49],[0,-0.81],[-0.41,-0.65],[-0.84,-0.34],[-1.18,0],[-1.37,0.84],[-1.12,0.37],[-1.4,-0.53],[-1.03,-1.12],[-0.32,-1.36],[0.78,-1.34],[1.12,-0.49],[2.61,-0.77],[3.3,0]],"o":[[-4.48,0],[-2.96,-1.62],[-1.71,-2.46],[-0.72,-2.58],[0,0],[0,-2.67],[0.71,-2.96],[1.71,-2.55],[2.96,-1.62],[4.17,0],[2.67,1.09],[1.49,1.65],[0.59,1.84],[0,2.43],[-0.93,1.59],[-1.53,0.9],[-1.96,0.44],[-2.08,0.22],[-1.49,0.13],[-0.47,0.5],[0,0.81],[0.4,0.65],[0.84,0.34],[1.37,0],[1.37,-0.84],[1.43,-0.5],[1.4,0.53],[1.03,1.12],[0.56,2.3],[-0.78,1.34],[-1.18,0.5],[-2.61,0.78],[0,0]],"v":[[1.165,25.39],[-9.995,22.96],[-16.995,16.84],[-20.635,9.28],[-21.705,2.33],[-21.705,0],[-20.635,-8.45],[-16.995,-16.71],[-9.995,-22.96],[1.165,-25.39],[11.435,-23.76],[17.685,-19.65],[20.815,-14.42],[21.705,-9.52],[20.305,-3.5],[16.615,0.23],[11.385,2.24],[5.315,3.22],[-0.705,3.83],[-3.645,4.76],[-4.345,6.72],[-3.735,8.91],[-1.865,10.4],[1.165,10.91],[5.275,9.65],[9.005,7.83],[13.255,7.88],[16.895,10.35],[18.905,14.08],[18.575,19.54],[15.725,22.29],[10.035,24.2],[1.165,25.37]]}}},{"ty":"fl","nm":"Fill 1","c":{"a":0,"k":[0,0.1451,0.2745]},"r":1,"o":{"a":0,"k":100}},{"ty":"tr","a":{"a":0,"k":[0,0]},"s":{"a":0,"k":[100,100]},"p":{"a":0,"k":[281.325,29.27]},"r":{"a":0,"k":0},"sa":{"a":0,"k":0},"o":{"a":0,"k":100}}]},{"ty":"gr","nm":"Group 4","it":[{"ty":"sh","nm":"Path 1","d":1,"ks":{"a":0,"k":{"c":true,"i":[[0,0],[-1.09,0.65],[-0.72,1.21],[0,1.55],[-0.13,1.59],[0,1.43],[0.15,0.25],[0.37,0.37],[0.65,0.16],[0.93,0],[0.78,-0.52],[0.43,-0.96],[0.16,-1.33],[0,-1.61],[0,0],[-0.43,-0.99],[-1.3,0]],"o":[[1.31,0],[1.09,-0.65],[0.71,-1.21],[0,-1.99],[0.12,-1.59],[0,-0.62],[-0.16,-0.25],[-0.37,-0.25],[-0.65,-0.16],[-1.31,0],[-0.78,0.53],[-0.44,0.96],[-0.16,1.34],[0,0],[0,3.11],[0.43,1],[0,0]],"v":[[-2.42,0.645],[1.17,-0.335],[3.88,-3.135],[4.95,-7.285],[5.14,-12.655],[5.33,-17.185],[5.1,-18.495],[4.31,-19.425],[2.77,-20.035],[0.39,-20.265],[-2.74,-19.475],[-4.56,-17.235],[-5.45,-13.785],[-5.68,-9.355],[-5.68,-7.025],[-5.03,-0.865],[-2.42,0.625]]}}},{"ty":"sh","nm":"Path 2","d":1,"ks":{"a":0,"k":{"c":true,"i":[[0,0],[2.27,0.53],[1.31,0.44],[0.68,1.53],[-0.37,1.8],[-1.74,1.15],[-2.05,-0.74],[-1.22,-0.5],[-1.55,0],[-0.71,0.37],[-0.41,0.71],[-0.19,0.93],[0.22,0.15],[0.31,-0.06],[0.75,-0.28],[0.97,-0.22],[1.43,0],[2.62,2.09],[1.18,3.49],[0,4.24],[0,0],[-0.71,2.96],[-1.71,2.55],[-2.96,1.61],[-4.49,0],[-2.42,-0.5],[-1.93,-0.68],[-1.4,-1.55],[0.19,-2.18],[0.12,-2.8],[0.06,-2.61],[0,-2.77],[0,0],[0.75,-2.74],[1.74,-2.3],[2.92,-1.37],[4.42,0]],"o":[[-2.61,0],[-2.27,-0.53],[-1.81,-0.75],[-0.69,-1.53],[0.5,-2.43],[1.74,-1.15],[1.24,0.43],[1.21,0.5],[1.31,0],[0.71,-0.37],[0.4,-0.72],[0.19,-0.56],[-0.22,-0.16],[-0.5,0.12],[-0.75,0.28],[-0.96,0.22],[-4.23,0],[-2.61,-2.08],[-1.18,-3.48],[0,0],[0,-2.67],[0.71,-2.96],[1.71,-2.55],[2.96,-1.62],[3.23,0],[2.43,0.5],[1.99,0.75],[1.4,1.56],[-0.25,3.3],[-0.12,2.8],[-0.06,2.61],[0,0],[0,2.74],[-0.75,2.74],[-1.74,2.3],[-2.93,1.37],[0,0]],"v":[[-1.49,34.715],[-8.82,33.925],[-14.19,32.475],[-17.92,29.065],[-18.39,24.075],[-15.03,18.705],[-9.34,18.095],[-5.65,19.495],[-1.5,20.245],[1.53,19.685],[3.21,18.055],[4.1,15.585],[4.05,14.515],[3.26,14.375],[1.39,14.985],[-1.18,15.735],[-4.77,16.065],[-15.04,12.935],[-20.73,4.575],[-22.5,-7.005],[-22.5,-9.335],[-21.43,-17.785],[-17.79,-26.045],[-10.79,-32.295],[0.37,-34.725],[8.86,-33.975],[15.4,-32.205],[20.49,-28.755],[22.31,-23.155],[21.75,-14.005],[21.47,-5.885],[21.38,2.195],[21.38,11.385],[20.26,19.605],[16.53,27.165],[9.53,32.675],[-1.49,34.725]]}}},{"ty":"fl","nm":"Fill 1","c":{"a":0,"k":[0,0.1451,0.2745]},"r":1,"o":{"a":0,"k":100}},{"ty":"tr","a":{"a":0,"k":[0,0]},"s":{"a":0,"k":[100,100]},"p":{"a":0,"k":[233.29,38.615]},"r":{"a":0,"k":0},"sa":{"a":0,"k":0},"o":{"a":0,"k":100}}]},{"ty":"gr","nm":"Group 5","it":[{"ty":"sh","nm":"Path 1","d":1,"ks":{"a":0,"k":{"c":true,"i":[[0,0],[-1.65,1.34],[-2.12,0],[-0.9,-0.34],[-0.37,-1.06],[-0.44,-0.25],[-0.74,0.38],[-0.65,0.47],[-0.97,0.53],[-1.24,0.4],[-1.68,0],[-2.83,-3.79],[0,-7.96],[-0.04,-1.83],[-0.12,-1.8],[-0.31,-2.55],[1.84,-1.65],[2.74,0],[1.87,1.64],[-0.32,2.49],[-0.12,1.8],[-0.03,1.84],[0,2.61],[0.47,1.28],[1.25,0],[1.09,-0.78],[0.65,-1.33],[0,-1.68],[-0.04,-1.83],[-0.12,-1.8],[-0.31,-2.55],[1.84,-1.65],[2.74,0],[1.89,1.55],[-0.18,2.49],[-0.1,3.52],[0.09,3.58],[0.31,4.3]],"o":[[-0.19,-2.12],[1.65,-1.34],[1.12,0],[0.9,0.34],[0.12,0.56],[0.43,0.25],[0.37,-0.19],[0.65,-0.47],[0.96,-0.53],[1.24,-0.4],[6.16,0],[2.83,3.8],[0,2.61],[0.03,1.84],[0.12,1.81],[0.31,2.49],[-1.84,1.65],[-2.93,0],[-1.87,-1.64],[0.31,-2.55],[0.12,-1.8],[0.03,-1.83],[0,-3.36],[-0.47,-1.27],[-1.25,0],[-1.09,0.78],[-0.65,1.34],[0,2.61],[0.03,1.84],[0.12,1.81],[0.31,2.49],[-1.84,1.65],[-2.74,0],[-1.9,-1.55],[0.31,-4.36],[0.09,-3.51],[-0.09,-3.58],[0,0]],"v":[[-22.92,-17.295],[-20.73,-22.475],[-15.08,-24.485],[-12.05,-23.975],[-10.14,-21.875],[-9.3,-20.665],[-7.53,-20.855],[-5.99,-21.835],[-3.56,-23.325],[-0.25,-24.725],[4.14,-25.335],[17.63,-19.645],[21.88,-2.005],[21.93,4.665],[22.16,10.125],[22.81,16.655],[20.52,22.865],[13.66,25.335],[6.47,22.865],[4.14,16.655],[4.79,10.125],[5.02,4.665],[5.07,-2.005],[4.37,-8.965],[1.8,-10.875],[-1.61,-9.705],[-4.22,-6.535],[-5.2,-2.005],[-5.15,4.665],[-4.92,10.125],[-4.27,16.655],[-6.56,22.865],[-13.42,25.335],[-20.37,23.005],[-22.94,16.935],[-22.33,5.125],[-22.33,-5.515],[-22.94,-17.325]]}}},{"ty":"fl","nm":"Fill 1","c":{"a":0,"k":[0.2314,0.5098,0.9647]},"r":1,"o":{"a":0,"k":100}},{"ty":"tr","a":{"a":0,"k":[0,0]},"s":{"a":0,"k":[100,100]},"p":{"a":0,"k":[180.32,47.875]},"r":{"a":0,"k":0},"sa":{"a":0,"k":0},"o":{"a":0,"k":100}}]},{"ty":"gr","nm":"Group 6","it":[{"ty":"sh","nm":"Path 1","d":1,"ks":{"a":0,"k":{"c":true,"i":[[-0.63,0.06],[-0.75,0.56],[0,0.93],[0.31,0.5],[0.53,0.25],[0.68,0],[0.77,-0.37],[0.49,-0.75],[0,-1.06],[-0.62,-0.28]],"o":[[2.61,-0.12],[0.75,-0.56],[0,-0.75],[-0.31,-0.5],[-0.53,-0.25],[-1.06,0],[-0.78,0.37],[-0.5,0.75],[0,0.62],[0.62,0.28]],"v":[[-1.455,-7.38],[3.585,-8.41],[4.705,-10.65],[4.235,-12.52],[2.975,-13.64],[1.155,-14.01],[-1.595,-13.45],[-3.505,-11.77],[-4.255,-9.06],[-3.325,-7.71]]}}},{"ty":"sh","nm":"Path 2","d":1,"ks":{"a":0,"k":{"c":true,"i":[[0,0],[2.96,1.62],[1.71,2.46],[0.71,2.58],[0,2.05],[0,0],[-0.71,2.96],[-1.71,2.55],[-2.96,1.61],[-4.49,0],[-2.68,-1.08],[-1.49,-1.65],[-0.59,-1.84],[0,-1.43],[0.93,-1.59],[1.53,-0.9],[1.96,-0.44],[2.09,-0.22],[1.93,-0.19],[0.47,-0.49],[0,-0.81],[-0.41,-0.65],[-0.84,-0.34],[-1.18,0],[-1.37,0.84],[-1.12,0.37],[-1.4,-0.53],[-1.03,-1.12],[-0.32,-1.36],[0.78,-1.34],[1.12,-0.49],[2.61,-0.77],[3.3,0]],"o":[[-4.48,0],[-2.96,-1.62],[-1.71,-2.46],[-0.72,-2.58],[0,0],[0,-2.67],[0.71,-2.96],[1.71,-2.55],[2.96,-1.62],[4.17,0],[2.67,1.09],[1.49,1.65],[0.59,1.84],[0,2.43],[-0.93,1.59],[-1.53,0.9],[-1.96,0.44],[-2.08,0.22],[-1.49,0.13],[-0.47,0.5],[0,0.81],[0.4,0.65],[0.84,0.34],[1.37,0],[1.37,-0.84],[1.43,-0.5],[1.4,0.53],[1.03,1.12],[0.56,2.3],[-0.78,1.34],[-1.18,0.5],[-2.61,0.78],[0,0]],"v":[[1.165,25.39],[-9.995,22.96],[-16.995,16.84],[-20.635,9.28],[-21.705,2.33],[-21.705,0],[-20.635,-8.45],[-16.995,-16.71],[-9.995,-22.96],[1.165,-25.39],[11.435,-23.76],[17.685,-19.65],[20.815,-14.42],[21.705,-9.52],[20.305,-3.5],[16.615,0.23],[11.385,2.24],[5.315,3.22],[-0.705,3.83],[-3.645,4.76],[-4.345,6.72],[-3.735,8.91],[-1.865,10.4],[1.165,10.91],[5.275,9.65],[9.005,7.83],[13.255,7.88],[16.895,10.35],[18.905,14.08],[18.575,19.54],[15.725,22.29],[10.035,24.2],[1.165,25.37]]}}},{"ty":"fl","nm":"Fill 1","c":{"a":0,"k":[0.2314,0.5098,0.9647]},"r":1,"o":{"a":0,"k":100}},{"ty":"tr","a":{"a":0,"k":[0,0]},"s":{"a":0,"k":[100,100]},"p":{"a":0,"k":[128.245,47.85]},"r":{"a":0,"k":0},"sa":{"a":0,"k":0},"o":{"a":0,"k":100}}]},{"ty":"gr","nm":"Group 7","it":[{"ty":"sh","nm":"Path 1","d":1,"ks":{"a":0,"k":{"c":true,"i":[[1.68,0],[1.49,0.71],[0.87,1.28],[-0.13,1.68],[-0.1,3.55],[0.09,3.55],[0.31,4.17],[-0.87,1.24],[-1.5,0.72],[-1.68,0],[-1.52,-1.53],[0,-2.49],[-0.04,-3.58],[-0.12,-3.58],[-0.31,-4.17],[0.87,-1.27],[1.43,-0.72]],"o":[[-1.68,0],[-1.49,-0.72],[-0.87,-1.28],[0.31,-4.17],[0.09,-3.55],[-0.09,-3.55],[-0.12,-1.74],[0.87,-1.25],[1.49,-0.71],[2.49,0],[1.52,1.53],[0,4.17],[0.03,3.58],[0.12,3.58],[0.12,1.68],[-0.87,1.28],[-1.43,0.71]],"v":[[0.095,36.495],[-4.665,35.425],[-8.215,32.435],[-9.335,28.005],[-8.725,16.425],[-8.725,5.785],[-9.335,-5.795],[-8.215,-10.275],[-4.665,-13.215],[0.095,-14.285],[6.115,-11.995],[8.405,-5.975],[8.455,5.645],[8.685,16.385],[9.335,28.005],[8.215,32.435],[4.765,35.425]]}}},{"ty":"sh","nm":"Path 2","d":1,"ks":{"a":0,"k":{"c":true,"i":[[0,0],[1.55,0.93],[0.93,1.55],[0,1.86],[-0.93,1.56],[-1.55,0.91],[-1.86,0],[-1.56,-0.9],[-0.91,-1.56],[0,-1.93],[1.77,-2.03],[3.3,0]],"o":[[-1.87,0],[-1.56,-0.93],[-0.93,-1.55],[0,-1.86],[0.93,-1.55],[1.56,-0.9],[1.86,0],[1.55,0.9],[0.9,1.56],[0,2.8],[-1.77,2.02],[0,0]],"v":[[-0.005,-15.965],[-5.135,-17.365],[-8.865,-21.095],[-10.265,-26.225],[-8.865,-31.455],[-5.135,-35.145],[-0.005,-36.495],[5.225,-35.145],[8.915,-31.455],[10.265,-26.225],[7.605,-18.985],[-0.005,-15.955]]}}},{"ty":"fl","nm":"Fill 1","c":{"a":0,"k":[0.2314,0.5098,0.9647]},"r":1,"o":{"a":0,"k":100}},{"ty":"tr","a":{"a":0,"k":[0,0]},"s":{"a":0,"k":[100,100]},"p":{"a":0,"k":[90.905,36.745]},"r":{"a":0,"k":0},"sa":{"a":0,"k":0},"o":{"a":0,"k":100}}]},{"ty":"gr","nm":"Group 8","it":[{"ty":"sh","nm":"Path 1","d":1,"ks":{"a":0,"k":{"c":true,"i":[[0,0],[1.46,0.71],[0.87,1.28],[-0.13,1.68],[-0.1,3.52],[0.09,3.58],[0.31,4.23],[-1.65,1.33],[-2.12,0],[-0.69,-0.37],[-0.38,-0.75],[-0.28,-0.22],[-0.25,0.18],[-0.78,0.47],[-1.05,0.5],[-1.4,0.31],[-1.74,0],[-0.59,-0.03],[-0.44,-0.06],[-1.25,-1.86],[0.93,-2.86],[1.06,-1.06],[1.31,-0.31],[1.25,0.93],[0.28,0.13],[0.37,0],[1.09,-0.78],[0.65,-1.33],[0,-1.68],[-0.04,-1.83],[-0.12,-1.8],[-0.31,-2.55],[0.84,-1.34],[1.53,-0.75],[1.8,0]],"o":[[-1.62,0],[-1.46,-0.72],[-0.87,-1.28],[0.31,-4.36],[0.09,-3.52],[-0.09,-3.58],[-0.19,-2.18],[1.65,-1.34],[1.12,0],[0.68,0.37],[0.44,0.62],[0.28,0.22],[0.5,-0.37],[0.78,-0.47],[1.06,-0.5],[1.4,-0.31],[0.62,0],[0.59,0.03],[2.24,0.25],[1.24,1.87],[-0.44,1.31],[-1.06,1.06],[-1.31,0.31],[-0.25,-0.19],[-0.28,-0.12],[-1.18,0],[-1.09,0.78],[-0.65,1.34],[0,2.61],[0.03,1.84],[0.12,1.81],[0.25,1.68],[-0.84,1.34],[-1.53,0.75],[0,0]],"v":[[-9.19,25.385],[-13.81,24.315],[-17.31,21.325],[-18.43,16.895],[-17.82,5.085],[-17.82,-5.555],[-18.43,-17.265],[-16.24,-22.535],[-10.59,-24.545],[-7.88,-23.985],[-6.29,-22.305],[-5.22,-21.045],[-4.43,-20.995],[-2.52,-22.255],[0.23,-23.705],[3.92,-24.915],[8.63,-25.385],[10.45,-25.335],[11.99,-25.195],[17.22,-22.025],[17.69,-14.935],[15.45,-11.385],[11.9,-9.335],[8.07,-10.265],[7.28,-10.735],[6.3,-10.925],[2.89,-9.755],[0.28,-6.585],[-0.7,-2.055],[-0.65,4.615],[-0.42,10.075],[0.23,16.605],[-0.66,21.135],[-4.21,24.265],[-9.2,25.385]]}}},{"ty":"fl","nm":"Fill 1","c":{"a":0,"k":[0.2314,0.5098,0.9647]},"r":1,"o":{"a":0,"k":100}},{"ty":"tr","a":{"a":0,"k":[0,0]},"s":{"a":0,"k":[100,100]},"p":{"a":0,"k":[64.21,47.855]},"r":{"a":0,"k":0},"sa":{"a":0,"k":0},"o":{"a":0,"k":100}}]},{"ty":"gr","nm":"Group 9","it":[{"ty":"sh","nm":"Path 1","d":1,"ks":{"a":0,"k":{"c":true,"i":[[0,0],[1.43,-1.74],[2.36,0.25],[1.77,0.12],[1.77,0.03],[2.55,0],[0.28,-0.62],[-0.06,-0.74],[0,-0.49],[-0.04,-0.43],[0,-0.81],[-0.25,-0.34],[-0.44,0],[-2.52,0.06],[-2.99,0.44],[-1.19,-0.78],[-0.69,-1.33],[0,-1.68],[1.34,-1.34],[2.24,0],[2.36,-0.09],[1.87,-0.31],[0.21,-0.25],[0,-0.62],[-0.04,-1.4],[-0.12,-1.59],[-0.31,-2.55],[1.89,-1.43],[3.36,0],[1.68,1.4],[-0.06,2.24],[-0.1,5.45],[0.09,5.45],[0.31,6.03],[-1.68,1.37],[-2.24,0],[0,0],[-1.34,-1.36],[0,-2.3]],"o":[[0,2.3],[-1.43,1.74],[-2.43,-0.31],[-1.77,-0.12],[-1.77,-0.03],[-1.12,0],[-0.28,0.62],[0.12,0.87],[0,0.49],[0.03,0.44],[0.06,0.44],[0.25,0.34],[1.62,0],[2.52,-0.06],[1.55,-0.31],[1.18,0.78],[0.68,1.34],[0,2.24],[-1.34,1.34],[-3.11,0],[-2.37,0.09],[-0.5,0.06],[-0.22,0.25],[0,1.99],[0.03,1.4],[0.12,1.59],[0.25,2.37],[-1.9,1.43],[-2.24,0],[-1.68,-1.4],[0.31,-6.1],[0.09,-5.45],[-0.09,-5.45],[-0.06,-2.3],[1.68,-1.37],[0,0],[2.24,0],[1.34,1.37],[0,0]],"v":[[22.622,-25.45],[20.472,-19.38],[14.782,-17.14],[8.482,-17.79],[3.162,-18.02],[-3.328,-18.07],[-5.428,-17.14],[-5.758,-15.09],[-5.568,-13.04],[-5.518,-11.64],[-5.468,-9.77],[-4.998,-8.6],[-3.968,-8.09],[2.242,-8.18],[10.502,-8.93],[14.612,-8.23],[17.412,-5.06],[18.442,-0.53],[16.432,4.84],[11.062,6.85],[2.852,6.99],[-3.498,7.6],[-4.568,8.07],[-4.898,9.38],[-4.848,14.47],[-4.618,18.95],[-3.968,25.16],[-6.438,30.85],[-14.328,33],[-20.208,30.9],[-22.638,25.44],[-22.028,8.12],[-22.028,-8.22],[-22.638,-25.44],[-20.208,-30.95],[-14.328,-33],[15.262,-33],[20.632,-30.95],[22.642,-25.44]]}}},{"ty":"fl","nm":"Fill 1","c":{"a":0,"k":[0.2314,0.5098,0.9647]},"r":1,"o":{"a":0,"k":100}},{"ty":"tr","a":{"a":0,"k":[0,0]},"s":{"a":0,"k":[100,100]},"p":{"a":0,"k":[22.948,40.06]},"r":{"a":0,"k":0},"sa":{"a":0,"k":0},"o":{"a":0,"k":100}}]}],"ind":5}],"v":"5.7.0","fr":29.97,"op":105.70064516129031,"ip":0,"assets":[]}